travis_log_fetch
