Metadata-Version: 1.1
Name: travis-log-fetch
Version: 0.1.1
Summary: Command line tool to fetch Travis-CI logs.
Home-page: https://github.com/jayvdb/travis_log_fetch
Author: John Vandenberg
Author-email: jayvdb@gmail.com
License: MIT
Download-URL: https://github.com/jayvdb/travis_log_fetch/tarball/0.1.1
Keywords: travis,travis-ci,travispy
Platform: UNKNOWN
Classifier: Development Status :: 4 - Beta
Classifier: Environment :: Console
Classifier: Intended Audience :: Developers
Classifier: License :: OSI Approved :: MIT License
Classifier: Natural Language :: English
Classifier: Operating System :: MacOS :: MacOS X
Classifier: Operating System :: Microsoft :: Windows
Classifier: Operating System :: POSIX
Classifier: Operating System :: POSIX :: Linux
Classifier: Operating System :: Unix
Classifier: Programming Language :: Python
Classifier: Programming Language :: Python :: 2
Classifier: Programming Language :: Python :: 3
Classifier: Topic :: Software Development :: Libraries
Classifier: Topic :: Software Development :: Quality Assurance
Classifier: Topic :: Software Development :: Testing
Classifier: Topic :: Utilities
